{
  "0": [
    "glass",
    null,
    "martini-glass-empty"
  ],
  "1": [
    "envelope-o",
    "far",
    "envelope"
  ],
  "2": [
    "star-o",
    "far",
    "star"
  ],
  "3": [
    "remove",
    null,
    "xmark"
  ],
  "4": [
    "close",
    null,
    "xmark"
  ],
  "5": [
    "gear",
    null,
    "gear"
  ],
  "6": [
    "trash-o",
    "far",
    "trash-can"
  ],
  "7": [
    "home",
    null,
    "house"
  ],
  "8": [
    "file-o",
    "far",
    "file"
  ],
  "9": [
    "clock-o",
    "far",
    "clock"
  ],
  "10": [
    "arrow-circle-o-down",
    "far",
    "circle-down"
  ],
  "11": [
    "arrow-circle-o-up",
    "far",
    "circle-up"
  ],
  "12": [
    "play-circle-o",
    "far",
    "circle-play"
  ],
  "13": [
    "repeat",
    null,
    "arrow-rotate-right"
  ],
  "14": [
    "rotate-right",
    null,
    "arrow-rotate-right"
  ],
  "15": [
    "refresh",
    null,
    "arrows-rotate"
  ],
  "16": [
    "list-alt",
    "far",
    "rectangle-list"
  ],
  "17": [
    "dedent",
    null,
    "outdent"
  ],
  "18": [
    "video-camera",
    null,
    "video"
  ],
  "19": [
    "picture-o",
    "far",
    "image"
  ],
  "20": [
    "photo",
    "far",
    "image"
  ],
  "21": [
    "image",
    "far",
    "image"
  ],
  "22": [
    "map-marker",
    null,
    "location-dot"
  ],
  "23": [
    "pencil-square-o",
    "far",
    "pen-to-square"
  ],
  "24": [
    "edit",
    "far",
    "pen-to-square"
  ],
  "25": [
    "share-square-o",
    null,
    "share-from-square"
  ],
  "26": [
    "check-square-o",
    "far",
    "square-check"
  ],
  "27": [
    "arrows",
    null,
    "up-down-left-right"
  ],
  "28": [
    "times-circle-o",
    "far",
    "circle-xmark"
  ],
  "29": [
    "check-circle-o",
    "far",
    "circle-check"
  ],
  "30": [
    "mail-forward",
    null,
    "share"
  ],
  "31": [
    "expand",
    null,
    "up-right-and-down-left-from-center"
  ],
  "32": [
    "compress",
    null,
    "down-left-and-up-right-to-center"
  ],
  "33": [
    "eye",
    "far",
    null
  ],
  "34": [
    "eye-slash",
    "far",
    null
  ],
  "35": [
    "warning",
    null,
    "triangle-exclamation"
  ],
  "36": [
    "calendar",
    null,
    "calendar-days"
  ],
  "37": [
    "arrows-v",
    null,
    "up-down"
  ],
  "38": [
    "arrows-h",
    null,
    "left-right"
  ],
  "39": [
    "bar-chart",
    null,
    "chart-column"
  ],
  "40": [
    "bar-chart-o",
    null,
    "chart-column"
  ],
  "41": [
    "twitter-square",
    "fab",
    null
  ],
  "42": [
    "facebook-square",
    "fab",
    null
  ],
  "43": [
    "gears",
    null,
    "gears"
  ],
  "44": [
    "thumbs-o-up",
    "far",
    "thumbs-up"
  ],
  "45": [
    "thumbs-o-down",
    "far",
    "thumbs-down"
  ],
  "46": [
    "heart-o",
    "far",
    "heart"
  ],
  "47": [
    "sign-out",
    null,
    "right-from-bracket"
  ],
  "48": [
    "linkedin-square",
    "fab",
    "linkedin"
  ],
  "49": [
    "thumb-tack",
    null,
    "thumbtack"
  ],
  "50": [
    "external-link",
    null,
    "up-right-from-square"
  ],
  "51": [
    "sign-in",
    null,
    "right-to-bracket"
  ],
  "52": [
    "github-square",
    "fab",
    null
  ],
  "53": [
    "lemon-o",
    "far",
    "lemon"
  ],
  "54": [
    "square-o",
    "far",
    "square"
  ],
  "55": [
    "bookmark-o",
    "far",
    "bookmark"
  ],
  "56": [
    "twitter",
    "fab",
    null
  ],
  "57": [
    "facebook",
    "fab",
    "facebook-f"
  ],
  "58": [
    "facebook-f",
    "fab",
    "facebook-f"
  ],
  "59": [
    "github",
    "fab",
    null
  ],
  "60": [
    "credit-card",
    "far",
    null
  ],
  "61": [
    "feed",
    null,
    "rss"
  ],
  "62": [
    "hdd-o",
    "far",
    "hard-drive"
  ],
  "63": [
    "hand-o-right",
    "far",
    "hand-point-right"
  ],
  "64": [
    "hand-o-left",
    "far",
    "hand-point-left"
  ],
  "65": [
    "hand-o-up",
    "far",
    "hand-point-up"
  ],
  "66": [
    "hand-o-down",
    "far",
    "hand-point-down"
  ],
  "67": [
    "globe",
    null,
    "earth-americas"
  ],
  "68": [
    "tasks",
    null,
    "bars-progress"
  ],
  "69": [
    "arrows-alt",
    null,
    "maximize"
  ],
  "70": [
    "group",
    null,
    "users"
  ],
  "71": [
    "chain",
    null,
    "link"
  ],
  "72": [
    "cut",
    null,
    "scissors"
  ],
  "73": [
    "files-o",
    "far",
    "copy"
  ],
  "74": [
    "floppy-o",
    "far",
    "floppy-disk"
  ],
  "75": [
    "save",
    "far",
    "floppy-disk"
  ],
  "76": [
    "navicon",
    null,
    "bars"
  ],
  "77": [
    "reorder",
    null,
    "bars"
  ],
  "78": [
    "magic",
    null,
    "wand-magic-sparkles"
  ],
  "79": [
    "pinterest",
    "fab",
    null
  ],
  "80": [
    "pinterest-square",
    "fab",
    null
  ],
  "81": [
    "google-plus-square",
    "fab",
    null
  ],
  "82": [
    "google-plus",
    "fab",
    "google-plus-g"
  ],
  "83": [
    "money",
    null,
    "money-bill-1"
  ],
  "84": [
    "unsorted",
    null,
    "sort"
  ],
  "85": [
    "sort-desc",
    null,
    "sort-down"
  ],
  "86": [
    "sort-asc",
    null,
    "sort-up"
  ],
  "87": [
    "linkedin",
    "fab",
    "linkedin-in"
  ],
  "88": [
    "rotate-left",
    null,
    "arrow-rotate-left"
  ],
  "89": [
    "legal",
    null,
    "gavel"
  ],
  "90": [
    "tachometer",
    null,
    "gauge-high"
  ],
  "91": [
    "dashboard",
    null,
    "gauge-high"
  ],
  "92": [
    "comment-o",
    "far",
    "comment"
  ],
  "93": [
    "comments-o",
    "far",
    "comments"
  ],
  "94": [
    "flash",
    null,
    "bolt"
  ],
  "95": [
    "clipboard",
    null,
    "paste"
  ],
  "96": [
    "lightbulb-o",
    "far",
    "lightbulb"
  ],
  "97": [
    "exchange",
    null,
    "right-left"
  ],
  "98": [
    "cloud-download",
    null,
    "cloud-arrow-down"
  ],
  "99": [
    "cloud-upload",
    null,
    "cloud-arrow-up"
  ],
  "100": [
    "bell-o",
    "far",
    "bell"
  ],
  "101": [
    "cutlery",
    null,
    "utensils"
  ],
  "102": [
    "file-text-o",
    "far",
    "file-lines"
  ],
  "103": [
    "building-o",
    "far",
    "building"
  ],
  "104": [
    "hospital-o",
    "far",
    "hospital"
  ],
  "105": [
    "tablet",
    null,
    "tablet-screen-button"
  ],
  "106": [
    "mobile",
    null,
    "mobile-screen-button"
  ],
  "107": [
    "mobile-phone",
    null,
    "mobile-screen-button"
  ],
  "108": [
    "circle-o",
    "far",
    "circle"
  ],
  "109": [
    "mail-reply",
    null,
    "reply"
  ],
  "110": [
    "github-alt",
    "fab",
    null
  ],
  "111": [
    "folder-o",
    "far",
    "folder"
  ],
  "112": [
    "folder-open-o",
    "far",
    "folder-open"
  ],
  "113": [
    "smile-o",
    "far",
    "face-smile"
  ],
  "114": [
    "frown-o",
    "far",
    "face-frown"
  ],
  "115": [
    "meh-o",
    "far",
    "face-meh"
  ],
  "116": [
    "keyboard-o",
    "far",
    "keyboard"
  ],
  "117": [
    "flag-o",
    "far",
    "flag"
  ],
  "118": [
    "mail-reply-all",
    null,
    "reply-all"
  ],
  "119": [
    "star-half-o",
    "far",
    "star-half-stroke"
  ],
  "120": [
    "star-half-empty",
    "far",
    "star-half-stroke"
  ],
  "121": [
    "star-half-full",
    "far",
    "star-half-stroke"
  ],
  "122": [
    "code-fork",
    null,
    "code-branch"
  ],
  "123": [
    "chain-broken",
    null,
    "link-slash"
  ],
  "124": [
    "unlink",
    null,
    "link-slash"
  ],
  "125": [
    "calendar-o",
    "far",
    "calendar"
  ],
  "126": [
    "maxcdn",
    "fab",
    null
  ],
  "127": [
    "html5",
    "fab",
    null
  ],
  "128": [
    "css3",
    "fab",
    null
  ],
  "129": [
    "unlock-alt",
    null,
    "unlock"
  ],
  "130": [
    "minus-square-o",
    "far",
    "square-minus"
  ],
  "131": [
    "level-up",
    null,
    "turn-up"
  ],
  "132": [
    "level-down",
    null,
    "turn-down"
  ],
  "133": [
    "pencil-square",
    null,
    "square-pen"
  ],
  "134": [
    "external-link-square",
    null,
    "square-up-right"
  ],
  "135": [
    "compass",
    "far",
    null
  ],
  "136": [
    "caret-square-o-down",
    "far",
    "square-caret-down"
  ],
  "137": [
    "toggle-down",
    "far",
    "square-caret-down"
  ],
  "138": [
    "caret-square-o-up",
    "far",
    "square-caret-up"
  ],
  "139": [
    "toggle-up",
    "far",
    "square-caret-up"
  ],
  "140": [
    "caret-square-o-right",
    "far",
    "square-caret-right"
  ],
  "141": [
    "toggle-right",
    "far",
    "square-caret-right"
  ],
  "142": [
    "eur",
    null,
    "euro-sign"
  ],
  "143": [
    "euro",
    null,
    "euro-sign"
  ],
  "144": [
    "gbp",
    null,
    "sterling-sign"
  ],
  "145": [
    "usd",
    null,
    "dollar-sign"
  ],
  "146": [
    "dollar",
    null,
    "dollar-sign"
  ],
  "147": [
    "inr",
    null,
    "indian-rupee-sign"
  ],
  "148": [
    "rupee",
    null,
    "indian-rupee-sign"
  ],
  "149": [
    "jpy",
    null,
    "yen-sign"
  ],
  "150": [
    "cny",
    null,
    "yen-sign"
  ],
  "151": [
    "rmb",
    null,
    "yen-sign"
  ],
  "152": [
    "yen",
    null,
    "yen-sign"
  ],
  "153": [
    "rub",
    null,
    "ruble-sign"
  ],
  "154": [
    "ruble",
    null,
    "ruble-sign"
  ],
  "155": [
    "rouble",
    null,
    "ruble-sign"
  ],
  "156": [
    "krw",
    null,
    "won-sign"
  ],
  "157": [
    "won",
    null,
    "won-sign"
  ],
  "158": [
    "btc",
    "fab",
    null
  ],
  "159": [
    "bitcoin",
    "fab",
    "btc"
  ],
  "160": [
    "file-text",
    null,
    "file-lines"
  ],
  "161": [
    "sort-alpha-asc",
    null,
    "arrow-down-a-z"
  ],
  "162": [
    "sort-alpha-desc",
    null,
    "arrow-down-z-a"
  ],
  "163": [
    "sort-amount-asc",
    null,
    "arrow-down-short-wide"
  ],
  "164": [
    "sort-amount-desc",
    null,
    "arrow-down-wide-short"
  ],
  "165": [
    "sort-numeric-asc",
    null,
    "arrow-down-1-9"
  ],
  "166": [
    "sort-numeric-desc",
    null,
    "arrow-down-9-1"
  ],
  "167": [
    "youtube-square",
    "fab",
    null
  ],
  "168": [
    "youtube",
    "fab",
    null
  ],
  "169": [
    "xing",
    "fab",
    null
  ],
  "170": [
    "xing-square",
    "fab",
    null
  ],
  "171": [
    "youtube-play",
    "fab",
    "youtube"
  ],
  "172": [
    "dropbox",
    "fab",
    null
  ],
  "173": [
    "stack-overflow",
    "fab",
    null
  ],
  "174": [
    "instagram",
    "fab",
    null
  ],
  "175": [
    "flickr",
    "fab",
    null
  ],
  "176": [
    "adn",
    "fab",
    null
  ],
  "177": [
    "bitbucket",
    "fab",
    null
  ],
  "178": [
    "bitbucket-square",
    "fab",
    "bitbucket"
  ],
  "179": [
    "tumblr",
    "fab",
    null
  ],
  "180": [
    "tumblr-square",
    "fab",
    null
  ],
  "181": [
    "long-arrow-down",
    null,
    "down-long"
  ],
  "182": [
    "long-arrow-up",
    null,
    "up-long"
  ],
  "183": [
    "long-arrow-left",
    null,
    "left-long"
  ],
  "184": [
    "long-arrow-right",
    null,
    "right-long"
  ],
  "185": [
    "apple",
    "fab",
    null
  ],
  "186": [
    "windows",
    "fab",
    null
  ],
  "187": [
    "android",
    "fab",
    null
  ],
  "188": [
    "linux",
    "fab",
    null
  ],
  "189": [
    "dribbble",
    "fab",
    null
  ],
  "190": [
    "skype",
    "fab",
    null
  ],
  "191": [
    "foursquare",
    "fab",
    null
  ],
  "192": [
    "trello",
    "fab",
    null
  ],
  "193": [
    "gratipay",
    "fab",
    null
  ],
  "194": [
    "gittip",
    "fab",
    "gratipay"
  ],
  "195": [
    "sun-o",
    "far",
    "sun"
  ],
  "196": [
    "moon-o",
    "far",
    "moon"
  ],
  "197": [
    "vk",
    "fab",
    null
  ],
  "198": [
    "weibo",
    "fab",
    null
  ],
  "199": [
    "renren",
    "fab",
    null
  ],
  "200": [
    "pagelines",
    "fab",
    null
  ],
  "201": [
    "stack-exchange",
    "fab",
    null
  ],
  "202": [
    "arrow-circle-o-right",
    "far",
    "circle-right"
  ],
  "203": [
    "arrow-circle-o-left",
    "far",
    "circle-left"
  ],
  "204": [
    "caret-square-o-left",
    "far",
    "square-caret-left"
  ],
  "205": [
    "toggle-left",
    "far",
    "square-caret-left"
  ],
  "206": [
    "dot-circle-o",
    "far",
    "circle-dot"
  ],
  "207": [
    "vimeo-square",
    "fab",
    null
  ],
  "208": [
    "try",
    null,
    "turkish-lira-sign"
  ],
  "209": [
    "turkish-lira",
    null,
    "turkish-lira-sign"
  ],
  "210": [
    "plus-square-o",
    "far",
    "square-plus"
  ],
  "211": [
    "slack",
    "fab",
    null
  ],
  "212": [
    "wordpress",
    "fab",
    null
  ],
  "213": [
    "openid",
    "fab",
    null
  ],
  "214": [
    "institution",
    null,
    "building-columns"
  ],
  "215": [
    "bank",
    null,
    "building-columns"
  ],
  "216": [
    "mortar-board",
    null,
    "graduation-cap"
  ],
  "217": [
    "yahoo",
    "fab",
    null
  ],
  "218": [
    "google",
    "fab",
    null
  ],
  "219": [
    "reddit",
    "fab",
    null
  ],
  "220": [
    "reddit-square",
    "fab",
    null
  ],
  "221": [
    "stumbleupon-circle",
    "fab",
    null
  ],
  "222": [
    "stumbleupon",
    "fab",
    null
  ],
  "223": [
    "delicious",
    "fab",
    null
  ],
  "224": [
    "digg",
    "fab",
    null
  ],
  "225": [
    "pied-piper-pp",
    "fab",
    null
  ],
  "226": [
    "pied-piper-alt",
    "fab",
    null
  ],
  "227": [
    "drupal",
    "fab",
    null
  ],
  "228": [
    "joomla",
    "fab",
    null
  ],
  "229": [
    "behance",
    "fab",
    null
  ],
  "230": [
    "behance-square",
    "fab",
    null
  ],
  "231": [
    "steam",
    "fab",
    null
  ],
  "232": [
    "steam-square",
    "fab",
    null
  ],
  "233": [
    "automobile",
    null,
    "car"
  ],
  "234": [
    "cab",
    null,
    "taxi"
  ],
  "235": [
    "spotify",
    "fab",
    null
  ],
  "236": [
    "deviantart",
    "fab",
    null
  ],
  "237": [
    "soundcloud",
    "fab",
    null
  ],
  "238": [
    "file-pdf-o",
    "far",
    "file-pdf"
  ],
  "239": [
    "file-word-o",
    "far",
    "file-word"
  ],
  "240": [
    "file-excel-o",
    "far",
    "file-excel"
  ],
  "241": [
    "file-powerpoint-o",
    "far",
    "file-powerpoint"
  ],
  "242": [
    "file-image-o",
    "far",
    "file-image"
  ],
  "243": [
    "file-photo-o",
    "far",
    "file-image"
  ],
  "244": [
    "file-picture-o",
    "far",
    "file-image"
  ],
  "245": [
    "file-archive-o",
    "far",
    "file-zipper"
  ],
  "246": [
    "file-zip-o",
    "far",
    "file-zipper"
  ],
  "247": [
    "file-audio-o",
    "far",
    "file-audio"
  ],
  "248": [
    "file-sound-o",
    "far",
    "file-audio"
  ],
  "249": [
    "file-video-o",
    "far",
    "file-video"
  ],
  "250": [
    "file-movie-o",
    "far",
    "file-video"
  ],
  "251": [
    "file-code-o",
    "far",
    "file-code"
  ],
  "252": [
    "vine",
    "fab",
    null
  ],
  "253": [
    "codepen",
    "fab",
    null
  ],
  "254": [
    "jsfiddle",
    "fab",
    null
  ],
  "255": [
    "life-bouy",
    null,
    "life-ring"
  ],
  "256": [
    "life-buoy",
    null,
    "life-ring"
  ],
  "257": [
    "life-saver",
    null,
    "life-ring"
  ],
  "258": [
    "support",
    null,
    "life-ring"
  ],
  "259": [
    "circle-o-notch",
    null,
    "circle-notch"
  ],
  "260": [
    "rebel",
    "fab",
    null
  ],
  "261": [
    "ra",
    "fab",
    "rebel"
  ],
  "262": [
    "resistance",
    "fab",
    "rebel"
  ],
  "263": [
    "empire",
    "fab",
    null
  ],
  "264": [
    "ge",
    "fab",
    "empire"
  ],
  "265": [
    "git-square",
    "fab",
    null
  ],
  "266": [
    "git",
    "fab",
    null
  ],
  "267": [
    "hacker-news",
    "fab",
    null
  ],
  "268": [
    "y-combinator-square",
    "fab",
    "hacker-news"
  ],
  "269": [
    "yc-square",
    "fab",
    "hacker-news"
  ],
  "270": [
    "tencent-weibo",
    "fab",
    null
  ],
  "271": [
    "qq",
    "fab",
    null
  ],
  "272": [
    "weixin",
    "fab",
    null
  ],
  "273": [
    "wechat",
    "fab",
    "weixin"
  ],
  "274": [
    "send",
    null,
    "paper-plane"
  ],
  "275": [
    "paper-plane-o",
    "far",
    "paper-plane"
  ],
  "276": [
    "send-o",
    "far",
    "paper-plane"
  ],
  "277": [
    "circle-thin",
    "far",
    "circle"
  ],
  "278": [
    "header",
    null,
    "heading"
  ],
  "279": [
    "futbol-o",
    "far",
    "futbol"
  ],
  "280": [
    "soccer-ball-o",
    "far",
    "futbol"
  ],
  "281": [
    "slideshare",
    "fab",
    null
  ],
  "282": [
    "twitch",
    "fab",
    null
  ],
  "283": [
    "yelp",
    "fab",
    null
  ],
  "284": [
    "newspaper-o",
    "far",
    "newspaper"
  ],
  "285": [
    "paypal",
    "fab",
    null
  ],
  "286": [
    "google-wallet",
    "fab",
    null
  ],
  "287": [
    "cc-visa",
    "fab",
    null
  ],
  "288": [
    "cc-mastercard",
    "fab",
    null
  ],
  "289": [
    "cc-discover",
    "fab",
    null
  ],
  "290": [
    "cc-amex",
    "fab",
    null
  ],
  "291": [
    "cc-paypal",
    "fab",
    null
  ],
  "292": [
    "cc-stripe",
    "fab",
    null
  ],
  "293": [
    "bell-slash-o",
    "far",
    "bell-slash"
  ],
  "294": [
    "trash",
    null,
    "trash-can"
  ],
  "295": [
    "copyright",
    "far",
    null
  ],
  "296": [
    "eyedropper",
    null,
    "eye-dropper"
  ],
  "297": [
    "area-chart",
    null,
    "chart-area"
  ],
  "298": [
    "pie-chart",
    null,
    "chart-pie"
  ],
  "299": [
    "line-chart",
    null,
    "chart-line"
  ],
  "300": [
    "lastfm",
    "fab",
    null
  ],
  "301": [
    "lastfm-square",
    "fab",
    null
  ],
  "302": [
    "ioxhost",
    "fab",
    null
  ],
  "303": [
    "angellist",
    "fab",
    null
  ],
  "304": [
    "cc",
    "far",
    "closed-captioning"
  ],
  "305": [
    "ils",
    null,
    "shekel-sign"
  ],
  "306": [
    "shekel",
    null,
    "shekel-sign"
  ],
  "307": [
    "sheqel",
    null,
    "shekel-sign"
  ],
  "308": [
    "buysellads",
    "fab",
    null
  ],
  "309": [
    "connectdevelop",
    "fab",
    null
  ],
  "310": [
    "dashcube",
    "fab",
    null
  ],
  "311": [
    "forumbee",
    "fab",
    null
  ],
  "312": [
    "leanpub",
    "fab",
    null
  ],
  "313": [
    "sellsy",
    "fab",
    null
  ],
  "314": [
    "shirtsinbulk",
    "fab",
    null
  ],
  "315": [
    "simplybuilt",
    "fab",
    null
  ],
  "316": [
    "skyatlas",
    "fab",
    null
  ],
  "317": [
    "diamond",
    "far",
    "gem"
  ],
  "318": [
    "transgender",
    null,
    "mars-and-venus"
  ],
  "319": [
    "intersex",
    null,
    "mars-and-venus"
  ],
  "320": [
    "transgender-alt",
    null,
    "transgender"
  ],
  "321": [
    "facebook-official",
    "fab",
    "facebook"
  ],
  "322": [
    "pinterest-p",
    "fab",
    null
  ],
  "323": [
    "whatsapp",
    "fab",
    null
  ],
  "324": [
    "hotel",
    null,
    "bed"
  ],
  "325": [
    "viacoin",
    "fab",
    null
  ],
  "326": [
    "medium",
    "fab",
    null
  ],
  "327": [
    "y-combinator",
    "fab",
    null
  ],
  "328": [
    "yc",
    "fab",
    "y-combinator"
  ],
  "329": [
    "optin-monster",
    "fab",
    null
  ],
  "330": [
    "opencart",
    "fab",
    null
  ],
  "331": [
    "expeditedssl",
    "fab",
    null
  ],
  "332": [
    "battery-4",
    null,
    "battery-full"
  ],
  "333": [
    "battery",
    null,
    "battery-full"
  ],
  "334": [
    "battery-3",
    null,
    "battery-three-quarters"
  ],
  "335": [
    "battery-2",
    null,
    "battery-half"
  ],
  "336": [
    "battery-1",
    null,
    "battery-quarter"
  ],
  "337": [
    "battery-0",
    null,
    "battery-empty"
  ],
  "338": [
    "object-group",
    "far",
    null
  ],
  "339": [
    "object-ungroup",
    "far",
    null
  ],
  "340": [
    "sticky-note-o",
    "far",
    "note-sticky"
  ],
  "341": [
    "cc-jcb",
    "fab",
    null
  ],
  "342": [
    "cc-diners-club",
    "fab",
    null
  ],
  "343": [
    "clone",
    "far",
    null
  ],
  "344": [
    "hourglass-o",
    null,
    "hourglass-empty"
  ],
  "345": [
    "hourglass-1",
    null,
    "hourglass-start"
  ],
  "346": [
    "hourglass-half",
    null,
    "hourglass"
  ],
  "347": [
    "hourglass-2",
    null,
    "hourglass"
  ],
  "348": [
    "hourglass-3",
    null,
    "hourglass-end"
  ],
  "349": [
    "hand-rock-o",
    "far",
    "hand-back-fist"
  ],
  "350": [
    "hand-grab-o",
    "far",
    "hand-back-fist"
  ],
  "351": [
    "hand-paper-o",
    "far",
    "hand"
  ],
  "352": [
    "hand-stop-o",
    "far",
    "hand"
  ],
  "353": [
    "hand-scissors-o",
    "far",
    "hand-scissors"
  ],
  "354": [
    "hand-lizard-o",
    "far",
    "hand-lizard"
  ],
  "355": [
    "hand-spock-o",
    "far",
    "hand-spock"
  ],
  "356": [
    "hand-pointer-o",
    "far",
    "hand-pointer"
  ],
  "357": [
    "hand-peace-o",
    "far",
    "hand-peace"
  ],
  "358": [
    "registered",
    "far",
    null
  ],
  "359": [
    "creative-commons",
    "fab",
    null
  ],
  "360": [
    "gg",
    "fab",
    null
  ],
  "361": [
    "gg-circle",
    "fab",
    null
  ],
  "362": [
    "odnoklassniki",
    "fab",
    null
  ],
  "363": [
    "odnoklassniki-square",
    "fab",
    null
  ],
  "364": [
    "get-pocket",
    "fab",
    null
  ],
  "365": [
    "wikipedia-w",
    "fab",
    null
  ],
  "366": [
    "safari",
    "fab",
    null
  ],
  "367": [
    "chrome",
    "fab",
    null
  ],
  "368": [
    "firefox",
    "fab",
    null
  ],
  "369": [
    "opera",
    "fab",
    null
  ],
  "370": [
    "internet-explorer",
    "fab",
    null
  ],
  "371": [
    "television",
    null,
    "tv"
  ],
  "372": [
    "contao",
    "fab",
    null
  ],
  "373": [
    "500px",
    "fab",
    null
  ],
  "374": [
    "amazon",
    "fab",
    null
  ],
  "375": [
    "calendar-plus-o",
    "far",
    "calendar-plus"
  ],
  "376": [
    "calendar-minus-o",
    "far",
    "calendar-minus"
  ],
  "377": [
    "calendar-times-o",
    "far",
    "calendar-xmark"
  ],
  "378": [
    "calendar-check-o",
    "far",
    "calendar-check"
  ],
  "379": [
    "map-o",
    "far",
    "map"
  ],
  "380": [
    "commenting",
    null,
    "comment-dots"
  ],
  "381": [
    "commenting-o",
    "far",
    "comment-dots"
  ],
  "382": [
    "houzz",
    "fab",
    null
  ],
  "383": [
    "vimeo",
    "fab",
    "vimeo-v"
  ],
  "384": [
    "black-tie",
    "fab",
    null
  ],
  "385": [
    "fonticons",
    "fab",
    null
  ],
  "386": [
    "reddit-alien",
    "fab",
    null
  ],
  "387": [
    "edge",
    "fab",
    null
  ],
  "388": [
    "credit-card-alt",
    null,
    "credit-card"
  ],
  "389": [
    "codiepie",
    "fab",
    null
  ],
  "390": [
    "modx",
    "fab",
    null
  ],
  "391": [
    "fort-awesome",
    "fab",
    null
  ],
  "392": [
    "usb",
    "fab",
    null
  ],
  "393": [
    "product-hunt",
    "fab",
    null
  ],
  "394": [
    "mixcloud",
    "fab",
    null
  ],
  "395": [
    "scribd",
    "fab",
    null
  ],
  "396": [
    "pause-circle-o",
    "far",
    "circle-pause"
  ],
  "397": [
    "stop-circle-o",
    "far",
    "circle-stop"
  ],
  "398": [
    "bluetooth",
    "fab",
    null
  ],
  "399": [
    "bluetooth-b",
    "fab",
    null
  ],
  "400": [
    "gitlab",
    "fab",
    null
  ],
  "401": [
    "wpbeginner",
    "fab",
    null
  ],
  "402": [
    "wpforms",
    "fab",
    null
  ],
  "403": [
    "envira",
    "fab",
    null
  ],
  "404": [
    "wheelchair-alt",
    "fab",
    "accessible-icon"
  ],
  "405": [
    "question-circle-o",
    "far",
    "circle-question"
  ],
  "406": [
    "volume-control-phone",
    null,
    "phone-volume"
  ],
  "407": [
    "asl-interpreting",
    null,
    "hands-asl-interpreting"
  ],
  "408": [
    "deafness",
    null,
    "ear-deaf"
  ],
  "409": [
    "hard-of-hearing",
    null,
    "ear-deaf"
  ],
  "410": [
    "glide",
    "fab",
    null
  ],
  "411": [
    "glide-g",
    "fab",
    null
  ],
  "412": [
    "signing",
    null,
    "hands"
  ],
  "413": [
    "viadeo",
    "fab",
    null
  ],
  "414": [
    "viadeo-square",
    "fab",
    null
  ],
  "415": [
    "snapchat",
    "fab",
    null
  ],
  "416": [
    "snapchat-ghost",
    "fab",
    "snapchat"
  ],
  "417": [
    "snapchat-square",
    "fab",
    null
  ],
  "418": [
    "pied-piper",
    "fab",
    null
  ],
  "419": [
    "first-order",
    "fab",
    null
  ],
  "420": [
    "yoast",
    "fab",
    null
  ],
  "421": [
    "themeisle",
    "fab",
    null
  ],
  "422": [
    "google-plus-official",
    "fab",
    "google-plus"
  ],
  "423": [
    "google-plus-circle",
    "fab",
    "google-plus"
  ],
  "424": [
    "font-awesome",
    "fab",
    null
  ],
  "425": [
    "fa",
    "fab",
    "font-awesome"
  ],
  "426": [
    "handshake-o",
    "far",
    "handshake"
  ],
  "427": [
    "envelope-open-o",
    "far",
    "envelope-open"
  ],
  "428": [
    "linode",
    "fab",
    null
  ],
  "429": [
    "address-book-o",
    "far",
    "address-book"
  ],
  "430": [
    "vcard",
    null,
    "address-card"
  ],
  "431": [
    "address-card-o",
    "far",
    "address-card"
  ],
  "432": [
    "vcard-o",
    "far",
    "address-card"
  ],
  "433": [
    "user-circle-o",
    "far",
    "circle-user"
  ],
  "434": [
    "user-o",
    "far",
    "user"
  ],
  "435": [
    "id-badge",
    "far",
    null
  ],
  "436": [
    "drivers-license",
    null,
    "id-card"
  ],
  "437": [
    "id-card-o",
    "far",
    "id-card"
  ],
  "438": [
    "drivers-license-o",
    "far",
    "id-card"
  ],
  "439": [
    "quora",
    "fab",
    null
  ],
  "440": [
    "free-code-camp",
    "fab",
    null
  ],
  "441": [
    "telegram",
    "fab",
    null
  ],
  "442": [
    "thermometer-4",
    null,
    "temperature-full"
  ],
  "443": [
    "thermometer",
    null,
    "temperature-full"
  ],
  "444": [
    "thermometer-3",
    null,
    "temperature-three-quarters"
  ],
  "445": [
    "thermometer-2",
    null,
    "temperature-half"
  ],
  "446": [
    "thermometer-1",
    null,
    "temperature-quarter"
  ],
  "447": [
    "thermometer-0",
    null,
    "temperature-empty"
  ],
  "448": [
    "bathtub",
    null,
    "bath"
  ],
  "449": [
    "s15",
    null,
    "bath"
  ],
  "450": [
    "window-maximize",
    "far",
    null
  ],
  "451": [
    "window-restore",
    "far",
    null
  ],
  "452": [
    "times-rectangle",
    null,
    "rectangle-xmark"
  ],
  "453": [
    "window-close-o",
    "far",
    "rectangle-xmark"
  ],
  "454": [
    "times-rectangle-o",
    "far",
    "rectangle-xmark"
  ],
  "455": [
    "bandcamp",
    "fab",
    null
  ],
  "456": [
    "grav",
    "fab",
    null
  ],
  "457": [
    "etsy",
    "fab",
    null
  ],
  "458": [
    "imdb",
    "fab",
    null
  ],
  "459": [
    "ravelry",
    "fab",
    null
  ],
  "460": [
    "eercast",
    "fab",
    "sellcast"
  ],
  "461": [
    "snowflake-o",
    "far",
    "snowflake"
  ],
  "462": [
    "superpowers",
    "fab",
    null
  ],
  "463": [
    "wpexplorer",
    "fab",
    null
  ],
  "464": [
    "meetup",
    "fab",
    null
  ],
  "465": [
    61440,
    "fas",
    "martini-glass-empty"
  ],
  "466": [
    61443,
    "far",
    "envelope"
  ],
  "467": [
    61446,
    "far",
    "star"
  ],
  "468": [
    61460,
    "far",
    "trash-can"
  ],
  "469": [
    61462,
    "far",
    "file"
  ],
  "470": [
    61463,
    "far",
    "clock"
  ],
  "471": [
    61466,
    "far",
    "circle-down"
  ],
  "472": [
    61467,
    "far",
    "circle-up"
  ],
  "473": [
    61469,
    "far",
    "circle-play"
  ],
  "474": [
    61470,
    "fas",
    "arrow-rotate-right"
  ],
  "475": [
    61474,
    "far",
    "rectangle-list"
  ],
  "476": [
    61502,
    "far",
    "image"
  ],
  "477": [
    61505,
    "fas",
    "location-dot"
  ],
  "478": [
    61508,
    "far",
    "pen-to-square"
  ],
  "479": [
    61509,
    "fas",
    "share-from-square"
  ],
  "480": [
    61510,
    "far",
    "square-check"
  ],
  "481": [
    61511,
    "fas",
    "up-down-left-right"
  ],
  "482": [
    61532,
    "far",
    "circle-xmark"
  ],
  "483": [
    61533,
    "far",
    "circle-check"
  ],
  "484": [
    61541,
    "fas",
    "up-right-and-down-left-from-center"
  ],
  "485": [
    61542,
    "fas",
    "down-left-and-up-right-to-center"
  ],
  "486": [
    61550,
    "far",
    "eye"
  ],
  "487": [
    61552,
    "far",
    "eye-slash"
  ],
  "488": [
    61555,
    "fas",
    "calendar-days"
  ],
  "489": [
    61565,
    "fas",
    "up-down"
  ],
  "490": [
    61566,
    "fas",
    "left-right"
  ],
  "491": [
    61568,
    "fas",
    "chart-column"
  ],
  "492": [
    61569,
    "fab",
    "twitter-square"
  ],
  "493": [
    61570,
    "fab",
    "facebook-square"
  ],
  "494": [
    61575,
    "far",
    "thumbs-up"
  ],
  "495": [
    61576,
    "far",
    "thumbs-down"
  ],
  "496": [
    61578,
    "far",
    "heart"
  ],
  "497": [
    61579,
    "fas",
    "right-from-bracket"
  ],
  "498": [
    61580,
    "fab",
    "linkedin"
  ],
  "499": [
    61582,
    "fas",
    "up-right-from-square"
  ],
  "500": [
    61584,
    "fas",
    "right-to-bracket"
  ],
  "501": [
    61586,
    "fab",
    "github-square"
  ],
  "502": [
    61588,
    "far",
    "lemon"
  ],
  "503": [
    61590,
    "far",
    "square"
  ],
  "504": [
    61591,
    "far",
    "bookmark"
  ],
  "505": [
    61593,
    "fab",
    "twitter"
  ],
  "506": [
    61594,
    "fab",
    "facebook-f"
  ],
  "507": [
    61595,
    "fab",
    "github"
  ],
  "508": [
    61597,
    "far",
    "credit-card"
  ],
  "509": [
    61600,
    "far",
    "hard-drive"
  ],
  "510": [
    61604,
    "far",
    "hand-point-right"
  ],
  "511": [
    61605,
    "far",
    "hand-point-left"
  ],
  "512": [
    61606,
    "far",
    "hand-point-up"
  ],
  "513": [
    61607,
    "far",
    "hand-point-down"
  ],
  "514": [
    61612,
    "fas",
    "earth-americas"
  ],
  "515": [
    61614,
    "fas",
    "bars-progress"
  ],
  "516": [
    61618,
    "fas",
    "maximize"
  ],
  "517": [
    61632,
    "fas",
    "users"
  ],
  "518": [
    61637,
    "far",
    "copy"
  ],
  "519": [
    61639,
    "far",
    "floppy-disk"
  ],
  "520": [
    61641,
    "fas",
    "bars"
  ],
  "521": [
    61648,
    "fas",
    "wand-magic-sparkles"
  ],
  "522": [
    61650,
    "fab",
    "pinterest"
  ],
  "523": [
    61651,
    "fab",
    "pinterest-square"
  ],
  "524": [
    61652,
    "fab",
    "google-plus-square"
  ],
  "525": [
    61653,
    "fab",
    "google-plus-g"
  ],
  "526": [
    61654,
    "fas",
    "money-bill-1"
  ],
  "527": [
    61665,
    "fab",
    "linkedin-in"
  ],
  "528": [
    61666,
    "fas",
    "arrow-rotate-left"
  ],
  "529": [
    61668,
    "fas",
    "gauge-high"
  ],
  "530": [
    61669,
    "far",
    "comment"
  ],
  "531": [
    61670,
    "far",
    "comments"
  ],
  "532": [
    61671,
    "fas",
    "bolt"
  ],
  "533": [
    61674,
    "fas",
    "paste"
  ],
  "534": [
    61675,
    "far",
    "lightbulb"
  ],
  "535": [
    61676,
    "fas",
    "right-left"
  ],
  "536": [
    61602,
    "far",
    "bell"
  ],
  "537": [
    61685,
    "fas",
    "utensils"
  ],
  "538": [
    61686,
    "far",
    "file-lines"
  ],
  "539": [
    61687,
    "far",
    "building"
  ],
  "540": [
    61688,
    "far",
    "hospital"
  ],
  "541": [
    61706,
    "fas",
    "tablet-screen-button"
  ],
  "542": [
    61707,
    "fas",
    "mobile-screen-button"
  ],
  "543": [
    61708,
    "far",
    "circle"
  ],
  "544": [
    61714,
    "fas",
    "reply"
  ],
  "545": [
    61715,
    "fab",
    "github-alt"
  ],
  "546": [
    61716,
    "far",
    "folder"
  ],
  "547": [
    61717,
    "far",
    "folder-open"
  ],
  "548": [
    61720,
    "far",
    "face-smile"
  ],
  "549": [
    61721,
    "far",
    "face-frown"
  ],
  "550": [
    61722,
    "far",
    "face-meh"
  ],
  "551": [
    61724,
    "far",
    "keyboard"
  ],
  "552": [
    61725,
    "far",
    "flag"
  ],
  "553": [
    61731,
    "far",
    "star-half-stroke"
  ],
  "554": [
    61734,
    "fas",
    "code-branch"
  ],
  "555": [
    61747,
    "far",
    "calendar"
  ],
  "556": [
    61750,
    "fab",
    "maxcdn"
  ],
  "557": [
    61755,
    "fab",
    "html5"
  ],
  "558": [
    61756,
    "fab",
    "css3"
  ],
  "559": [
    61758,
    "fas",
    "unlock"
  ],
  "560": [
    61767,
    "far",
    "square-minus"
  ],
  "561": [
    61768,
    "fas",
    "turn-up"
  ],
  "562": [
    61769,
    "fas",
    "turn-down"
  ],
  "563": [
    61772,
    "fas",
    "square-up-right"
  ],
  "564": [
    61774,
    "far",
    "compass"
  ],
  "565": [
    61776,
    "far",
    "square-caret-down"
  ],
  "566": [
    61777,
    "far",
    "square-caret-up"
  ],
  "567": [
    61778,
    "far",
    "square-caret-right"
  ],
  "568": [
    61781,
    "fas",
    "dollar-sign"
  ],
  "569": [
    61782,
    "fas",
    "indian-rupee-sign"
  ],
  "570": [
    61786,
    "fab",
    "btc"
  ],
  "571": [
    61790,
    "fas",
    "arrow-down-z-a"
  ],
  "572": [
    61792,
    "fas",
    "arrow-down-short-wide"
  ],
  "573": [
    61793,
    "fas",
    "arrow-down-wide-short"
  ],
  "574": [
    61795,
    "fas",
    "arrow-down-9-1"
  ],
  "575": [
    61798,
    "fab",
    "youtube-square"
  ],
  "576": [
    61799,
    "fab",
    "youtube"
  ],
  "577": [
    61800,
    "fab",
    "xing"
  ],
  "578": [
    61801,
    "fab",
    "xing-square"
  ],
  "579": [
    61802,
    "fab",
    "youtube"
  ],
  "580": [
    61803,
    "fab",
    "dropbox"
  ],
  "581": [
    61804,
    "fab",
    "stack-overflow"
  ],
  "582": [
    61805,
    "fab",
    "instagram"
  ],
  "583": [
    61806,
    "fab",
    "flickr"
  ],
  "584": [
    61808,
    "fab",
    "adn"
  ],
  "585": [
    61809,
    "fab",
    "bitbucket"
  ],
  "586": [
    61810,
    "fab",
    "bitbucket"
  ],
  "587": [
    61811,
    "fab",
    "tumblr"
  ],
  "588": [
    61812,
    "fab",
    "tumblr-square"
  ],
  "589": [
    61813,
    "fas",
    "down-long"
  ],
  "590": [
    61814,
    "fas",
    "up-long"
  ],
  "591": [
    61815,
    "fas",
    "left-long"
  ],
  "592": [
    61816,
    "fas",
    "right-long"
  ],
  "593": [
    61817,
    "fab",
    "apple"
  ],
  "594": [
    61818,
    "fab",
    "windows"
  ],
  "595": [
    61819,
    "fab",
    "android"
  ],
  "596": [
    61820,
    "fab",
    "linux"
  ],
  "597": [
    61821,
    "fab",
    "dribbble"
  ],
  "598": [
    61822,
    "fab",
    "skype"
  ],
  "599": [
    61824,
    "fab",
    "foursquare"
  ],
  "600": [
    61825,
    "fab",
    "trello"
  ],
  "601": [
    61828,
    "fab",
    "gratipay"
  ],
  "602": [
    61829,
    "far",
    "sun"
  ],
  "603": [
    61830,
    "far",
    "moon"
  ],
  "604": [
    61833,
    "fab",
    "vk"
  ],
  "605": [
    61834,
    "fab",
    "weibo"
  ],
  "606": [
    61835,
    "fab",
    "renren"
  ],
  "607": [
    61836,
    "fab",
    "pagelines"
  ],
  "608": [
    61837,
    "fab",
    "stack-exchange"
  ],
  "609": [
    61838,
    "far",
    "circle-right"
  ],
  "610": [
    61840,
    "far",
    "circle-left"
  ],
  "611": [
    61841,
    "far",
    "square-caret-left"
  ],
  "612": [
    61842,
    "far",
    "circle-dot"
  ],
  "613": [
    61844,
    "fab",
    "vimeo-square"
  ],
  "614": [
    61845,
    "fas",
    "turkish-lira-sign"
  ],
  "615": [
    61846,
    "far",
    "square-plus"
  ],
  "616": [
    61848,
    "fab",
    "slack"
  ],
  "617": [
    61850,
    "fab",
    "wordpress"
  ],
  "618": [
    61851,
    "fab",
    "openid"
  ],
  "619": [
    61854,
    "fab",
    "yahoo"
  ],
  "620": [
    61856,
    "fab",
    "google"
  ],
  "621": [
    61857,
    "fab",
    "reddit"
  ],
  "622": [
    61858,
    "fab",
    "reddit-square"
  ],
  "623": [
    61859,
    "fab",
    "stumbleupon-circle"
  ],
  "624": [
    61860,
    "fab",
    "stumbleupon"
  ],
  "625": [
    61861,
    "fab",
    "delicious"
  ],
  "626": [
    61862,
    "fab",
    "digg"
  ],
  "627": [
    61863,
    "fab",
    "pied-piper-pp"
  ],
  "628": [
    61864,
    "fab",
    "pied-piper-alt"
  ],
  "629": [
    61865,
    "fab",
    "drupal"
  ],
  "630": [
    61866,
    "fab",
    "joomla"
  ],
  "631": [
    61876,
    "fab",
    "behance"
  ],
  "632": [
    61877,
    "fab",
    "behance-square"
  ],
  "633": [
    61878,
    "fab",
    "steam"
  ],
  "634": [
    61879,
    "fab",
    "steam-square"
  ],
  "635": [
    61884,
    "fab",
    "spotify"
  ],
  "636": [
    61885,
    "fab",
    "deviantart"
  ],
  "637": [
    61886,
    "fab",
    "soundcloud"
  ],
  "638": [
    61889,
    "far",
    "file-pdf"
  ],
  "639": [
    61890,
    "far",
    "file-word"
  ],
  "640": [
    61891,
    "far",
    "file-excel"
  ],
  "641": [
    61892,
    "far",
    "file-powerpoint"
  ],
  "642": [
    61893,
    "far",
    "file-image"
  ],
  "643": [
    61894,
    "far",
    "file-zipper"
  ],
  "644": [
    61895,
    "far",
    "file-audio"
  ],
  "645": [
    61896,
    "far",
    "file-video"
  ],
  "646": [
    61897,
    "far",
    "file-code"
  ],
  "647": [
    61898,
    "fab",
    "vine"
  ],
  "648": [
    61899,
    "fab",
    "codepen"
  ],
  "649": [
    61900,
    "fab",
    "jsfiddle"
  ],
  "650": [
    61901,
    "fas",
    "life-ring"
  ],
  "651": [
    61902,
    "fas",
    "circle-notch"
  ],
  "652": [
    61904,
    "fab",
    "rebel"
  ],
  "653": [
    61905,
    "fab",
    "empire"
  ],
  "654": [
    61906,
    "fab",
    "git-square"
  ],
  "655": [
    61907,
    "fab",
    "git"
  ],
  "656": [
    61908,
    "fab",
    "hacker-news"
  ],
  "657": [
    61909,
    "fab",
    "tencent-weibo"
  ],
  "658": [
    61910,
    "fab",
    "qq"
  ],
  "659": [
    61911,
    "fab",
    "weixin"
  ],
  "660": [
    61912,
    "fas",
    "paper-plane"
  ],
  "661": [
    61913,
    "far",
    "paper-plane"
  ],
  "662": [
    61915,
    "far",
    "circle"
  ],
  "663": [
    61923,
    "far",
    "futbol"
  ],
  "664": [
    61927,
    "fab",
    "slideshare"
  ],
  "665": [
    61928,
    "fab",
    "twitch"
  ],
  "666": [
    61929,
    "fab",
    "yelp"
  ],
  "667": [
    61930,
    "far",
    "newspaper"
  ],
  "668": [
    61933,
    "fab",
    "paypal"
  ],
  "669": [
    61934,
    "fab",
    "google-wallet"
  ],
  "670": [
    61936,
    "fab",
    "cc-visa"
  ],
  "671": [
    61937,
    "fab",
    "cc-mastercard"
  ],
  "672": [
    61938,
    "fab",
    "cc-discover"
  ],
  "673": [
    61939,
    "fab",
    "cc-amex"
  ],
  "674": [
    61940,
    "fab",
    "cc-paypal"
  ],
  "675": [
    61941,
    "fab",
    "cc-stripe"
  ],
  "676": [
    61943,
    "far",
    "bell-slash"
  ],
  "677": [
    61944,
    "fas",
    "trash-can"
  ],
  "678": [
    61945,
    "far",
    "copyright"
  ],
  "679": [
    61954,
    "fab",
    "lastfm"
  ],
  "680": [
    61955,
    "fab",
    "lastfm-square"
  ],
  "681": [
    61960,
    "fab",
    "ioxhost"
  ],
  "682": [
    61961,
    "fab",
    "angellist"
  ],
  "683": [
    61962,
    "far",
    "closed-captioning"
  ],
  "684": [
    61965,
    "fab",
    "buysellads"
  ],
  "685": [
    61966,
    "fab",
    "connectdevelop"
  ],
  "686": [
    61968,
    "fab",
    "dashcube"
  ],
  "687": [
    61969,
    "fab",
    "forumbee"
  ],
  "688": [
    61970,
    "fab",
    "leanpub"
  ],
  "689": [
    61971,
    "fab",
    "sellsy"
  ],
  "690": [
    61972,
    "fab",
    "shirtsinbulk"
  ],
  "691": [
    61973,
    "fab",
    "simplybuilt"
  ],
  "692": [
    61974,
    "fab",
    "skyatlas"
  ],
  "693": [
    61977,
    "far",
    "gem"
  ],
  "694": [
    61988,
    "fas",
    "mars-and-venus"
  ],
  "695": [
    62000,
    "fab",
    "facebook"
  ],
  "696": [
    62001,
    "fab",
    "pinterest-p"
  ],
  "697": [
    62002,
    "fab",
    "whatsapp"
  ],
  "698": [
    62006,
    "fas",
    "bed"
  ],
  "699": [
    62007,
    "fab",
    "viacoin"
  ],
  "700": [
    62010,
    "fab",
    "medium"
  ],
  "701": [
    62011,
    "fab",
    "y-combinator"
  ],
  "702": [
    62012,
    "fab",
    "optin-monster"
  ],
  "703": [
    62013,
    "fab",
    "opencart"
  ],
  "704": [
    62014,
    "fab",
    "expeditedssl"
  ],
  "705": [
    62016,
    "fas",
    "battery-full"
  ],
  "706": [
    62017,
    "fas",
    "battery-three-quarters"
  ],
  "707": [
    62018,
    "fas",
    "battery-half"
  ],
  "708": [
    62019,
    "fas",
    "battery-quarter"
  ],
  "709": [
    62023,
    "far",
    "object-group"
  ],
  "710": [
    62024,
    "far",
    "object-ungroup"
  ],
  "711": [
    62026,
    "far",
    "note-sticky"
  ],
  "712": [
    62027,
    "fab",
    "cc-jcb"
  ],
  "713": [
    62028,
    "fab",
    "cc-diners-club"
  ],
  "714": [
    62029,
    "far",
    "clone"
  ],
  "715": [
    62032,
    "fas",
    "hourglass-empty"
  ],
  "716": [
    62034,
    "fas",
    "hourglass"
  ],
  "717": [
    62037,
    "far",
    "hand-back-fist"
  ],
  "718": [
    62038,
    "far",
    "hand"
  ],
  "719": [
    62039,
    "far",
    "hand-scissors"
  ],
  "720": [
    62040,
    "far",
    "hand-lizard"
  ],
  "721": [
    62041,
    "far",
    "hand-spock"
  ],
  "722": [
    62042,
    "far",
    "hand-pointer"
  ],
  "723": [
    62043,
    "far",
    "hand-peace"
  ],
  "724": [
    62045,
    "far",
    "registered"
  ],
  "725": [
    62046,
    "fab",
    "creative-commons"
  ],
  "726": [
    62048,
    "fab",
    "gg"
  ],
  "727": [
    62049,
    "fab",
    "gg-circle"
  ],
  "728": [
    62051,
    "fab",
    "odnoklassniki"
  ],
  "729": [
    62052,
    "fab",
    "odnoklassniki-square"
  ],
  "730": [
    62053,
    "fab",
    "get-pocket"
  ],
  "731": [
    62054,
    "fab",
    "wikipedia-w"
  ],
  "732": [
    62055,
    "fab",
    "safari"
  ],
  "733": [
    62056,
    "fab",
    "chrome"
  ],
  "734": [
    62057,
    "fab",
    "firefox"
  ],
  "735": [
    62058,
    "fab",
    "opera"
  ],
  "736": [
    62059,
    "fab",
    "internet-explorer"
  ],
  "737": [
    62061,
    "fab",
    "contao"
  ],
  "738": [
    62062,
    "fab",
    "500px"
  ],
  "739": [
    62064,
    "fab",
    "amazon"
  ],
  "740": [
    62065,
    "far",
    "calendar-plus"
  ],
  "741": [
    62066,
    "far",
    "calendar-minus"
  ],
  "742": [
    62067,
    "far",
    "calendar-xmark"
  ],
  "743": [
    62068,
    "far",
    "calendar-check"
  ],
  "744": [
    62072,
    "far",
    "map"
  ],
  "745": [
    62074,
    "fas",
    "comment-dots"
  ],
  "746": [
    62075,
    "far",
    "comment-dots"
  ],
  "747": [
    62076,
    "fab",
    "houzz"
  ],
  "748": [
    62077,
    "fab",
    "vimeo-v"
  ],
  "749": [
    62078,
    "fab",
    "black-tie"
  ],
  "750": [
    62080,
    "fab",
    "fonticons"
  ],
  "751": [
    62081,
    "fab",
    "reddit-alien"
  ],
  "752": [
    62082,
    "fab",
    "edge"
  ],
  "753": [
    62083,
    "fas",
    "credit-card"
  ],
  "754": [
    62084,
    "fab",
    "codiepie"
  ],
  "755": [
    62085,
    "fab",
    "modx"
  ],
  "756": [
    62086,
    "fab",
    "fort-awesome"
  ],
  "757": [
    62087,
    "fab",
    "usb"
  ],
  "758": [
    62088,
    "fab",
    "product-hunt"
  ],
  "759": [
    62089,
    "fab",
    "mixcloud"
  ],
  "760": [
    62090,
    "fab",
    "scribd"
  ],
  "761": [
    62092,
    "far",
    "circle-pause"
  ],
  "762": [
    62094,
    "far",
    "circle-stop"
  ],
  "763": [
    62099,
    "fab",
    "bluetooth"
  ],
  "764": [
    62100,
    "fab",
    "bluetooth-b"
  ],
  "765": [
    62102,
    "fab",
    "gitlab"
  ],
  "766": [
    62103,
    "fab",
    "wpbeginner"
  ],
  "767": [
    62104,
    "fab",
    "wpforms"
  ],
  "768": [
    62105,
    "fab",
    "envira"
  ],
  "769": [
    62107,
    "fab",
    "accessible-icon"
  ],
  "770": [
    62108,
    "far",
    "circle-question"
  ],
  "771": [
    62117,
    "fab",
    "glide"
  ],
  "772": [
    62118,
    "fab",
    "glide-g"
  ],
  "773": [
    62121,
    "fab",
    "viadeo"
  ],
  "774": [
    62122,
    "fab",
    "viadeo-square"
  ],
  "775": [
    62123,
    "fab",
    "snapchat"
  ],
  "776": [
    62124,
    "fab",
    "snapchat"
  ],
  "777": [
    62125,
    "fab",
    "snapchat-square"
  ],
  "778": [
    62126,
    "fab",
    "pied-piper"
  ],
  "779": [
    62128,
    "fab",
    "first-order"
  ],
  "780": [
    62129,
    "fab",
    "yoast"
  ],
  "781": [
    62130,
    "fab",
    "themeisle"
  ],
  "782": [
    62131,
    "fab",
    "google-plus"
  ],
  "783": [
    62132,
    "fab",
    "font-awesome"
  ],
  "784": [
    62133,
    "far",
    "handshake"
  ],
  "785": [
    62135,
    "far",
    "envelope-open"
  ],
  "786": [
    62136,
    "fab",
    "linode"
  ],
  "787": [
    62138,
    "far",
    "address-book"
  ],
  "788": [
    62140,
    "far",
    "address-card"
  ],
  "789": [
    62142,
    "far",
    "circle-user"
  ],
  "790": [
    62144,
    "far",
    "user"
  ],
  "791": [
    62145,
    "far",
    "id-badge"
  ],
  "792": [
    62147,
    "far",
    "id-card"
  ],
  "793": [
    62148,
    "fab",
    "quora"
  ],
  "794": [
    62149,
    "fab",
    "free-code-camp"
  ],
  "795": [
    62150,
    "fab",
    "telegram"
  ],
  "796": [
    62151,
    "fas",
    "temperature-full"
  ],
  "797": [
    62157,
    "fas",
    "bath"
  ],
  "798": [
    62160,
    "far",
    "window-maximize"
  ],
  "799": [
    62162,
    "far",
    "window-restore"
  ],
  "800": [
    62163,
    "fas",
    "rectangle-xmark"
  ],
  "801": [
    62164,
    "far",
    "rectangle-xmark"
  ],
  "802": [
    62165,
    "fab",
    "bandcamp"
  ],
  "803": [
    62166,
    "fab",
    "grav"
  ],
  "804": [
    62167,
    "fab",
    "etsy"
  ],
  "805": [
    62168,
    "fab",
    "imdb"
  ],
  "806": [
    62169,
    "fab",
    "ravelry"
  ],
  "807": [
    62170,
    "fab",
    "sellcast"
  ],
  "808": [
    62172,
    "far",
    "snowflake"
  ],
  "809": [
    62173,
    "fab",
    "superpowers"
  ],
  "810": [
    62174,
    "fab",
    "wpexplorer"
  ],
  "811": [
    62176,
    "fab",
    "meetup"
  ]
}
