{
  "data": [
    {
      "id": "R_kgDOIi7DeQ",
      "name": "AsyncPywhatKit",
      "createdAt": "2022-12-02T15:30:28Z",
      "url": "https://github.com/SigireddyBalasai/AsyncPywhatKit",
      "description": "The purpose of the repository is to provide an asynchronous Python library with various helpful features for WhatsApp automation and YouTube It’s easy-to-use and does not require you to do any additional setup",
      "isFork": false,
      "languages": [
        {
          "name": "Python",
          "iconifyClass": "logos-python"
        }
      ]
    },
    {
      "id": "R_kgDOJIRdUw",
      "name": "whatpack.py",
      "createdAt": "2023-03-11T15:36:48Z",
      "url": "https://github.com/SigireddyBalasai/whatpack.py",
      "description": "whatpack.py is a Python package that allows you to automate WhatsApp and YouTube tasks in an asynchronous and headless way. It uses asyncpywhatkit and headlesspywhatkit libraries under the hood to provide fast and easy-to-use features. With whatpack.py, you can send messages on WhatsApp without opening the app",
      "isFork": false,
      "languages": [
        {
          "name": "Python",
          "iconifyClass": "logos-python"
        }
      ]
    }
  ]
}
